getcode/__init__.py
getcode/cli.py
getcode/clipboard.py
getcode/core.py
getcode/github_api.py
getcode/versioning.py
getcodes-0.1.5.dist-info/METADATA
getcodes-0.1.5.dist-info/WHEEL
getcodes-0.1.5.dist-info/entry_points.txt
getcodes-0.1.5.dist-info/top_level.txt
getcodes-0.1.5.dist-info/RECORD
