Metadata-Version: 2.4
Name: getcodes
Version: 0.1.5
Summary: CLI to browse and fetch code snippets from GetSomeSleepBro/codes via GitHub API
Author-email: getcode <noreply@example.com>
License: MIT
Project-URL: Homepage, https://github.com/GetSomeSleepBro/codes
Keywords: cli,github,codes,education,snippets
Classifier: Programming Language :: Python :: 3
Classifier: License :: OSI Approved :: MIT License
Classifier: Operating System :: OS Independent
Requires-Python: >=3.8
